fasttrig/__init__.py
fasttrig/sin.py
fasttrig-0.1.6.dist-info/METADATA
fasttrig-0.1.6.dist-info/WHEEL
fasttrig-0.1.6.dist-info/top_level.txt
fasttrig-0.1.6.dist-info/RECORD
