Metadata-Version: 2.4
Name: fasttrig
Version: 0.1.6
Summary: Fast sine/cosine/tangent approximation using fourth degree polynomials
Home-page: https://github.com/gnaixanna/fasttrig
Author: Yinyin Xiang
Author-email: realannaxiang@gmail.com
Classifier: Programming Language :: Python :: 3
Classifier: Intended Audience :: Developers
Classifier: License :: OSI Approved :: MIT License
Classifier: Operating System :: OS Independent
Requires-Python: >=3.6
Requires-Dist: numpy
Dynamic: author
Dynamic: author-email
Dynamic: classifier
Dynamic: description
Dynamic: description-content-type
Dynamic: home-page
Dynamic: requires-dist
Dynamic: requires-python
Dynamic: summary
